[
  {"name": "Annual", "notes": "Seeded plant type"},
  {"name": "Perennial", "notes": "Seeded plant type"},
  {"name": "Herb", "notes": "Seeded plant type"},
  {"name": "Vegetable", "notes": "Seeded plant type"},
  {"name": "Flowering", "notes": "Seeded plant type"},
  {"name": "Edible", "notes": "Seeded plant type"},
  {"name": "Indoor", "notes": "Seeded plant type"},
  {"name": "Outdoor", "notes": "Seeded plant type"},
  {"name": "Drought Tolerant", "notes": "Seeded plant type"},
  {"name": "Companion Plant", "notes": "Seeded plant type"}
]
